{
  "project_info": {
    "project_number": "253395548923",
    "firebase_url": "https://testcicdapp.firebaseio.com",
    "project_id": "testcicdapp",
    "storage_bucket": "testcicdapp.appspot.com"
  },
  "client": [
    {
      "client_info": {
        "mobilesdk_app_id": "1:253395548923:android:2e2674c9d40a2270b64e5e",
        "android_client_info": {
          "package_name": "com.orbismobile.testingforandroid"
        }
      },
      "oauth_client": [
        {
          "client_id": "253395548923-p0jquv6e2t2dl8bbn4n74osiih4j2vet.apps.googleusercontent.com",
          "client_type": 3
        }
      ],
      "api_key": [
        {
          "current_key": "AIzaSyA-7zUcQ1boXpniglLrobc5R-jBxRO8pQ4"
        }
      ],
      "services": {
        "appinvite_service": {
          "other_platform_oauth_client": [
            {
              "client_id": "253395548923-p0jquv6e2t2dl8bbn4n74osiih4j2vet.apps.googleusercontent.com",
              "client_type": 3
            }
          ]
        }
      }
    }
  ],
  "configuration_version": "1"
}